{
  "dataset": "refnerf",
  "scene": "teapot",
  "source_scene": "/data/liuly/dataset/3DGS/Shiny Blender Synthetic/teapot",
  "output_scene": "/data/liuly/dataset/3DGS/SparseViewGenerated/refnerf/uniform_pose/views_6/seed_0/teapot",
  "strategy": "uniform_pose",
  "seed": 0,
  "requested_views": 6,
  "train_frames_available": 100,
  "train_frames_selected": 6,
  "test_frames": 200,
  "selected_indices": [
    7,
    12,
    27,
    31,
    40,
    43
  ],
  "selected_file_paths": [
    "./train/r_7",
    "./train/r_12",
    "./train/r_27",
    "./train/r_31",
    "./train/r_40",
    "./train/r_43"
  ],
  "status": "ok",
  "notes": "",
  "dry_run": false,
  "reused_existing": false
}
